conpygure/__init__.py
conpygure-0.0.1.dist-info/LICENSE
conpygure-0.0.1.dist-info/METADATA
conpygure-0.0.1.dist-info/WHEEL
conpygure-0.0.1.dist-info/top_level.txt
conpygure-0.0.1.dist-info/RECORD
