Metadata-Version: 2.1
Name: conpygure
Version: 0.0.1
Summary: A library to con*py*gure little projects :) 
Home-page: https://github.com/LucaSoato/conpygure
Author: Luca Soato
Author-email: info@lucasoato.it
License: UNKNOWN
Platform: UNKNOWN
Requires-Dist: toml
